mcp_server_converter/__init__.py
mcp_server_converter/__main__.py
mcp_server_converter/converter.py
mcp_server_converter/units/__init__.py
mcp_server_converter/units/area.py
mcp_server_converter/units/data_transfer.py
mcp_server_converter/units/digital_storage.py
mcp_server_converter/units/energy.py
mcp_server_converter/units/frequency.py
mcp_server_converter/units/fuel_economy.py
mcp_server_converter/units/length.py
mcp_server_converter/units/mass.py
mcp_server_converter/units/power.py
mcp_server_converter/units/pressure.py
mcp_server_converter/units/speed.py
mcp_server_converter/units/temperature.py
mcp_server_converter/units/time.py
mcp_server_converter/units/volume.py
mcp_server_converter-0.2.0.dist-info/METADATA
mcp_server_converter-0.2.0.dist-info/WHEEL
mcp_server_converter-0.2.0.dist-info/entry_points.txt
mcp_server_converter-0.2.0.dist-info/RECORD
