Metadata-Version: 2.4
Name: mcp-server-converter
Version: 0.2.0
Summary: A Model Context Protocol server for length conversions
Project-URL: Source, https://github.com/moldach/mcp-server-converter
Author-email: Matthew Oldach <moldach686@gmail.com>
License: MIT
Keywords: calculator,llm,math,mcp
Classifier: Development Status :: 4 - Beta
Classifier: Intended Audience :: Developers
Classifier: License :: OSI Approved :: MIT License
Classifier: Programming Language :: Python :: 3
Classifier: Programming Language :: Python :: 3.10
Requires-Python: >=3.10
Requires-Dist: mcp>=1.4.1
